arxiv_cli/__init__.py
arxiv_cli/cli.py
arxiv_cli_tools-0.1.0.dist-info/METADATA
arxiv_cli_tools-0.1.0.dist-info/WHEEL
arxiv_cli_tools-0.1.0.dist-info/entry_points.txt
arxiv_cli_tools-0.1.0.dist-info/top_level.txt
arxiv_cli_tools-0.1.0.dist-info/RECORD
