Metadata-Version: 2.4
Name: arxiv-cli-tools
Version: 0.1.0
Summary: Command-line interface for searching and downloading arXiv papers.
Author: Marc Kotrotsos
Keywords: arxiv,cli,search,papers
Classifier: Development Status :: 3 - Alpha
Classifier: License :: OSI Approved :: MIT License
Classifier: Programming Language :: Python
Classifier: Programming Language :: Python :: 3
Classifier: Programming Language :: Python :: 3.9
Classifier: Programming Language :: Python :: 3.10
Classifier: Programming Language :: Python :: 3.11
Classifier: Programming Language :: Python :: 3.12
Classifier: Topic :: Internet :: WWW/HTTP :: Indexing/Search
Classifier: Topic :: Scientific/Engineering :: Information Analysis
Requires-Python: >=3.9
Requires-Dist: arxiv>=2.2.0
Requires-Dist: requests>=2.31
